py_tf2_currency/__init__.py
py_tf2_currency/currency.py
py_tf2_currency/currency_error.py
py_tf2_currency/currency_helper.py
py_tf2_currency/currency_interface.py
py_tf2_currency-0.2.0.dist-info/METADATA
py_tf2_currency-0.2.0.dist-info/WHEEL
py_tf2_currency-0.2.0.dist-info/top_level.txt
py_tf2_currency-0.2.0.dist-info/RECORD
