Metadata-Version: 2.1
Name: py_tf2_currency
Version: 0.2.0
Summary: UNKNOWN
Home-page: UNKNOWN
Author: Sachin/Derpy
License: UNKNOWN
Platform: UNKNOWN
